gwrefpy/__init__.py
gwrefpy/constants.py
gwrefpy/examples/deviation_example.gwref
gwrefpy/examples/large_example.gwref
gwrefpy/examples/small_example.gwref
gwrefpy/fitbase.py
gwrefpy/fitresults.py
gwrefpy/io/__init__.py
gwrefpy/io/io.py
gwrefpy/methods/__init__.py
gwrefpy/methods/chebyshev.py
gwrefpy/methods/common.py
gwrefpy/methods/linregressfit.py
gwrefpy/methods/npolyfit.py
gwrefpy/methods/timeseries.py
gwrefpy/model.py
gwrefpy/plotter.py
gwrefpy/utils/__init__.py
gwrefpy/utils/conversions.py
gwrefpy/utils/decorators.py
gwrefpy/utils/logger_config.py
gwrefpy/well.py
gwrefpy-0.4.0.dist-info/WHEEL
gwrefpy-0.4.0.dist-info/METADATA
gwrefpy-0.4.0.dist-info/RECORD
