Metadata-Version: 2.4
Name: gwrefpy
Version: 0.4.0
Summary: A python implementation of the Akvifär reference method for detecting deviations in groundwater level time series.
Author: Anders Retzner, Erik Toller, Tobias Erlström
Author-email: Anders Retzner <anders.retzner@gmail.com>
License-Expression: MIT
Classifier: Programming Language :: Python :: 3
Classifier: Programming Language :: Python :: 3.11
Classifier: Programming Language :: Python :: 3.12
Classifier: Programming Language :: Python :: 3.13
Classifier: License :: OSI Approved :: MIT License
Classifier: Operating System :: OS Independent
Requires-Dist: matplotlib>=3.10.5
Requires-Dist: numpy>=2.3.2
Requires-Dist: pandas>=2.3.2
Requires-Dist: scipy>=1.16.1
Requires-Python: >=3.11
